nonebot_plugin_githubcard/__init__.py
nonebot_plugin_githubcard/config.py
nonebot_plugin_githubcard/models.py
nonebot_plugin_githubcard/service.py
nonebot_plugin_githubcard-0.4.1.dist-info/licenses/LICENSE
nonebot_plugin_githubcard-0.4.1.dist-info/METADATA
nonebot_plugin_githubcard-0.4.1.dist-info/WHEEL
nonebot_plugin_githubcard-0.4.1.dist-info/RECORD
