Metadata-Version: 2.4
Name: nonebot-plugin-githubcard
Version: 0.4.1
Summary: 检测GitHub仓库链接并自动发送卡片信息，支持仓库、Issue、Pull Request、Release
License: MIT
License-File: LICENSE
Keywords: nonebot,github,card,bot
Author: Nanako
Author-email: demo0929@vip.qq.com
Requires-Python: >=3.8,<4.0
Classifier: Development Status :: 4 - Beta
Classifier: Framework :: Robot Framework :: Library
Classifier: License :: OSI Approved :: MIT License
Classifier: Operating System :: OS Independent
Classifier: Programming Language :: Python :: 3
Classifier: Programming Language :: Python :: 3.8
Classifier: Programming Language :: Python :: 3.9
Classifier: Programming Language :: Python :: 3.10
Classifier: Programming Language :: Python :: 3.11
Classifier: Programming Language :: Python :: 3.12
Classifier: Programming Language :: Python :: 3.13
Classifier: Programming Language :: Python :: 3.14
Classifier: Topic :: Communications :: Chat
Requires-Dist: aiohttp (>=3.7.4,<4.0.0)
Requires-Dist: nonebot-adapter-onebot (>=2.2.0,<3.0.0)
Requires-Dist: nonebot-plugin-alconna (>=0.30.0)
Requires-Dist: nonebot2 (>=2.0.0,<3.0.0)
Requires-Dist: pydantic (>=1.9.0)
Project-URL: Documentation, https://github.com/ElainaFanBoy/nonebot_plugin_githubcard#readme
Project-URL: Homepage, https://github.com/ElainaFanBoy/nonebot_plugin_githubcard
Project-URL: Repository, https://github.com/ElainaFanBoy/nonebot_plugin_githubcard
